odoo/addons/mrp_bom_component_menu/README.rst
odoo/addons/mrp_bom_component_menu/__init__.py
odoo/addons/mrp_bom_component_menu/__manifest__.py
odoo/addons/mrp_bom_component_menu/i18n/de.po
odoo/addons/mrp_bom_component_menu/i18n/mrp_bom_component_menu.pot
odoo/addons/mrp_bom_component_menu/i18n/zh_CN.po
odoo/addons/mrp_bom_component_menu/readme/CONTRIBUTORS.rst
odoo/addons/mrp_bom_component_menu/readme/DESCRIPTION.rst
odoo/addons/mrp_bom_component_menu/readme/USAGE.rst
odoo/addons/mrp_bom_component_menu/static/description/icon.png
odoo/addons/mrp_bom_component_menu/static/description/index.html
odoo/addons/mrp_bom_component_menu/views/mrp_bom_component_view.xml
odoo13_addon_mrp_bom_component_menu-13.0.1.0.0.dist-info/METADATA
odoo13_addon_mrp_bom_component_menu-13.0.1.0.0.dist-info/WHEEL
odoo13_addon_mrp_bom_component_menu-13.0.1.0.0.dist-info/top_level.txt
odoo13_addon_mrp_bom_component_menu-13.0.1.0.0.dist-info/RECORD
